tetsuya/__init__.py
tetsuya/_cache.py
tetsuya/_config.py
tetsuya/_process.py
tetsuya/_timer.py
tetsuya/service_manager.py
tetsuya/core/__init__.py
tetsuya/core/_serializer.py
tetsuya/core/utils.py
tetsuya/services/__init__.py
tetsuya/services/_base.py
tetsuya/services/search_git.py
tetsuya-0.2.0.dist-info/licenses/LICENSE
tetsuya-0.2.0.dist-info/METADATA
tetsuya-0.2.0.dist-info/WHEEL
tetsuya-0.2.0.dist-info/entry_points.txt
tetsuya-0.2.0.dist-info/top_level.txt
tetsuya-0.2.0.dist-info/RECORD
